yulain_test_project/__init__.py
yulain_test_project/__main__.py
yulain_test_project/test.py
yulain_test_project-0.0.1.dist-info/METADATA
yulain_test_project-0.0.1.dist-info/WHEEL
yulain_test_project-0.0.1.dist-info/entry_points.txt
yulain_test_project-0.0.1.dist-info/top_level.txt
yulain_test_project-0.0.1.dist-info/RECORD
