Metadata-Version: 2.1
Name: yulain-test-project
Version: 0.0.1
Summary: Just a demo project
Keywords: sample,project
Requires-Python: >=3.8
Requires-Dist: requests
Requires-Dist: psutil
